{
  "sEmptyTable": {
    "en": "No data available in table",
    "fr": "Aucune donn&eacute;e disponible dans le tableau",
    "de": "Keine Daten in der Tabelle vorhanden",
    "hr": "Nincs rendelkezésre álló adat",
    "cs": "Tabulka neobsahuje žádná data",
    "nl": "Geen resultaten aanwezig in de tabel",
    "fi": "Ei näytettäviä tuloksia.",
    "es": "Ningún dato disponible en esta tabla",
    "el": "Δεν υπάρχουν δεδομένα στον πίνακα",
    "hu": "Nincs rendelkezésre álló adat",
    "it": "Nessun dato presente nella tabella",
    "lv": "Tabulā nav datu",
    "lt": "Lentelėje nėra duomenų",
    "pl": "Brak danych",
    "pt": "Nenhum registro encontrado",
    "sk": "Nie sú k dispozícii žiadne dáta",
    "sl": "Nobenih podatkov ni na voljo",
    "sv": "Tabellen innehåller ingen data",
    "nn": "Inga data tilgjengeleg i tabellen",
    "nb": "Ingen data tilgjengelig i tabellen",
    "jp": "テーブルにデータがありません",
    "ru": "В таблице отсутствуют данные"
  },
  "sInfo": {
    "en": "Showing _START_ to _END_ of _TOTAL_ entries",
    "fr": "Affichage de l'&eacute;l&eacute;ment _START_ &agrave; _END_ sur _TOTAL_ &eacute;l&eacute;ments",
    "de": "_START_ bis _END_ von _TOTAL_ Einträgen",
    "bg": "Показване на резултати от _START_ до _END_ от общо _TOTAL_",
    "hr": "Találatok: _START_ - _END_ Összesen: _TOTAL_",
    "cs": "Zobrazuji _START_ až _END_ z celkem _TOTAL_ záznamů",
    "da": "Viser _START_ til _END_ af _TOTAL_ linjer",
    "nl": "_START_ tot _END_ van _TOTAL_ resultaten",
    "et": "Kuvatud: _TOTAL_ kirjet (_START_-_END_)",
    "fi": "Näytetään rivit _START_ - _END_ (yhteensä _TOTAL_ )",
    "es": "Mostrando registros del _START_ al _END_ de un total de _TOTAL_ registros",
    "el": "Εμφανίζονται _START_ έως _END_ από _TOTAL_ εγγραφές",
    "hu": "Találatok: _START_ - _END_ Összesen: _TOTAL_",
    "gd": "_START_ Showing a _END_ na n-iontrálacha  _TOTAL_",
    "it": "Vista da _START_ a _END_ di _TOTAL_ elementi",
    "lv": "Parādīti _START_ līdz _END_ no _TOTAL_ ierakstiem",
    "lt": "Rodomi įrašai nuo _START_ iki _END_ iš _TOTAL_ įrašų",
    "pl": "Pozycje od _START_ do _END_ z _TOTAL_ łącznie",
    "pt": "Mostrando de _START_ até _END_ de _TOTAL_ registos",
    "ro": "Afișate de la _START_ la _END_ din _TOTAL_ înregistrări",
    "sk": "Záznamy _START_ až _END_ z celkom _TOTAL_",
    "sl": "Prikazujem _START_ do _END_ od _TOTAL_ zapisov",
    "sv": "Visar _START_ till _END_ av totalt _TOTAL_ rader",
    "nn": "Syner _START_ til _END_ av _TOTAL_ linjer",
    "nb": "Viser _START_ til _END_ av _TOTAL_ linjer",
    "mt": "Entrata _START_ sa _END_ minn _TOTAL_",
    "ar": "إظهار _START_ إلى _END_ من أصل _TOTAL_ مدخل",
    "zh": "顯示第 _START_ 至 _END_ 項結果，共 _TOTAL_ 項",
    "jp": " _TOTAL_ 件中 _START_ から _END_ まで表示",
    "ru": "Записи с _START_ до _END_ из _TOTAL_ записей"
  },
  "sInfoEmpty": {
    "en": "Showing 0 to 0 of 0 entries",
    "fr": "Affichage de l'&eacute;l&eacute;ment 0 &agrave; 0 sur 0 &eacute;l&eacute;ment",
    "de": "Keine Daten vorhanden",
    "bg": "Показване на резултати от 0 до 0 от общо 0",
    "hr": "Nulla találat",
    "cs": "Zobrazuji 0 až 0 z 0 záznamů",
    "da": "Viser 0 til 0 af 0 linjer",
    "nl": "Geen resultaten om weer te geven",
    "et": "Otsinguvasteid ei leitud",
    "fi": "Näytetään 0 - 0 (yhteensä 0)",
    "es": "Mostrando registros del 0 al 0 de un total de 0 registros",
    "el": "Εμφανίζονται 0 έως 0 από 0 εγγραφές",
    "hu": "Nulla találat",
    "gd": "Showing 0-0 na n-iontrálacha  0",
    "it": "Vista da 0 a 0 di 0 elementi",
    "lv": "Nav ierakstu",
    "lt": "Rodomi įrašai nuo 0 iki 0 iš 0",
    "pl": "Pozycji 0 z 0 dostępnych",
    "pt": "Mostrando de 0 até 0 de 0 registos",
    "ro": "Afișate de la 0 la 0 din 0 înregistrări",
    "sk": "Záznamy 0 až 0 z celkom 0 ",
    "sl": "Prikazujem 0 do 0 od 0 zapisov",
    "sv": "Visar 0 till 0 av totalt 0 rader",
    "nn": "Syner 0 til 0 av 0 linjer",
    "nb": "Viser 0 til 0 av 0 linjer",
    "mt": "Entrata 0 sa 0 minn 0",
    "ar": "يعرض 0 إلى 0 من أصل 0 سجل",
    "zh": "顯示第 0 至 0 項結果，共 0 項",
    "jp": " 0 件中 0 から 0 まで表示",
    "ru": "Записи с 0 до 0 из 0 записей"
  },
  "sInfoFiltered": {
    "en": "(filtered from _MAX_ total entries)",
    "fr": "(filtr&eacute; de _MAX_ &eacute;l&eacute;ments au total)",
    "de": "(gefiltert von _MAX_ Einträgen)",
    "bg": "(филтрирани от общо _MAX_ резултата)",
    "hr": "(_MAX_ összes rekord közül szűrve)",
    "cs": "(filtrováno z celkem _MAX_ záznamů)",
    "da": "(filtreret fra _MAX_ linjer)",
    "nl": " (gefilterd uit _MAX_ resultaten)",
    "et": " - filteeritud _MAX_ kirje seast.",
    "fi": "(suodatettu _MAX_ tuloksen joukosta)",
    "es": "(filtrado de un total de _MAX_ registros)",
    "el": "(φιλτραρισμένες από _MAX_ συνολικά εγγραφές)",
    "hu": "(_MAX_ összes rekord közül szűrve)",
    "gd": "(scagtha ó _MAX_ iontrálacha iomlán)",
    "it": "(filtrati da _MAX_ elementi totali)",
    "lv": "(atlasīts no pavisam _MAX_ ierakstiem)",
    "lt": "(atrinkta iš _MAX_ įrašų)",
    "pl": "(filtrowanie spośród _MAX_ dostępnych pozycji)",
    "pt": "(filtrado de _MAX_ registos no total)",
    "ro": "(filtrate dintr-un total de _MAX_ înregistrări)",
    "sk": "(vyfiltrované spomedzi _MAX_ záznamov)",
    "sl": "(filtrirano od _MAX_ vseh zapisov)",
    "sv": "(filtrerade från totalt _MAX_ rader)",
    "nn": "(filtrert frå _MAX_ totalt antal linjer)",
    "nb": "(filtrert fra _MAX_ totalt antall linjer)",
    "mt": "(filter minn total ta' _MAX_)",
    "ar": "(منتقاة من مجموع _MAX_ مُدخل)",
    "zh": "(從 _MAX_ 項結果中過濾)",
    "jp": "（全 _MAX_ 件より抽出）",
    "ru": "(отфильтровано из _MAX_ записей)"
  },
  "sInfoPostFix": {
    "en": "",
    "fr": "",
    "de": "",
    "bg": "",
    "hr": "",
    "cs": "",
    "da": "",
    "nl": "",
    "et": "K&otilde;ik kuvatud kirjed p&otilde;hinevad reaalsetel tulemustel.",
    "fi": "",
    "es": "",
    "el": "",
    "hu": "",
    "gd": "",
    "it": "",
    "lv": "",
    "lt": "",
    "pl": "",
    "pt": "",
    "ro": "",
    "sk": "",
    "sl": "",
    "sv": "",
    "nn": "",
    "nb": "",
    "ar": "",
    "zh": "",
    "jp": "",
    "ru": ""
  },
  "sInfoThousands": {
    "en": ",",
    "de": ".",
    "hr": " ",
    "cs": " ",
    "nl": ".",
    "fi": ",",
    "es": ",",
    "el": ".",
    "hu": " ",
    "it": ".",
    "lt": " ",
    "sk": ",",
    "sl": ",",
    "sv": " ",
    "nn": " ",
    "nb": " ",
    "jp": ","
  },
  "sLengthMenu": {
    "en": "Show _MENU_ entries",
    "fr": "Afficher _MENU_ &eacute;l&eacute;ments",
    "de": "_MENU_ Einträge anzeigen",
    "bg": "Показване на _MENU_ резултата",
    "hr": "_MENU_ találat oldalanként",
    "cs": "Zobraz záznamů _MENU_",
    "da": "Vis _MENU_ linjer",
    "nl": "_MENU_ resultaten weergeven",
    "et": "N&auml;ita kirjeid _MENU_ kaupa",
    "fi": "Näytä kerralla _MENU_ riviä",
    "es": "Mostrar _MENU_ registros",
    "el": "Δείξε _MENU_ εγγραφές",
    "hu": "_MENU_ találat oldalanként",
    "gd": "Taispeáin iontrálacha _MENU_",
    "it": "Visualizza _MENU_ elementi",
    "lv": "Rādīt _MENU_ ierakstus",
    "lt": "Rodyti _MENU_ įrašus",
    "pl": "Pokaż _MENU_ pozycji",
    "pt": "Mostrar _MENU_ registos",
    "ro": "Afișează _MENU_ înregistrări pe pagină",
    "sk": "Zobraz _MENU_ záznamov",
    "sl": "Prikaži _MENU_ zapisov",
    "sv": "Visa _MENU_ rader",
    "nn": "Syn _MENU_ linjer",
    "nb": "Vis _MENU_ linjer",
    "mt": "Uri _MENU_ entrata/i",
    "ar": "أظهر _MENU_ مدخلات",
    "zh": "顯示 _MENU_ 項結果",
    "jp": "_MENU_ 件表示",
    "ru": "Показать _MENU_ записей"
  },
  "sLoadingRecords": {
    "en": "Loading...",
    "fr": "Chargement en cours...",
    "de": "Wird geladen ..",
    "hr": "Betöltés...",
    "cs": "Načítám...",
    "nl": "Een moment geduld aub - bezig met laden...",
    "fi": "Ladataan...",
    "es": "Cargando...",
    "el": "Φόρτωση...",
    "hu": "Betöltés...",
    "it": "Caricamento...",
    "lv": "Notiek ielāde ...",
    "lt": "Įkeliama...",
    "pl": "Wczytywanie...",
    "sk": "Načítavam...",
    "sl": "Nalagam...",
    "sv": "Laddar...",
    "nn": "Lastar...",
    "nb": "Laster...",
    "mt": "Qed jillowdja...",
    "zh": "載入中...",
    "jp": "読み込み中...",
    "ru": "Загрузка записей..."
  },
  "sProcessing": {
    "en": "Processing...",
    "fr": "Traitement en cours...",
    "de": "Bitte warten ..",
    "bg": "Обработка на резултатите...",
    "hr": "Feldolgozás...",
    "cs": "Provádím...",
    "da": "Henter...",
    "nl": "Bezig...",
    "et": "Palun oodake, koostan kuvamiseks nimekirja!",
    "fi": "Hetkinen...",
    "es": "Procesando...",
    "el": "Επεξεργασία...",
    "hu": "Feldolgozás...",
    "gd": "Próiseáil...",
    "it": "Elaborazione...",
    "lv": "Uzgaidiet ...",
    "lt": "Apdorojama...",
    "pl": "Przetwarzanie...",
    "pt": "A processar...",
    "ro": "Procesează...",
    "sk": "Spracúvam...",
    "sl": "Obdelujem...",
    "sv": "Bearbetar...",
    "nn": "Lastar...",
    "nb": "Laster...",
    "mt": "Qed jipproċessa...",
    "ar": "جارٍ التحميل...",
    "zh": "處理中...",
    "jp": "処理中...",
    "ru": "Подождите..."
  },
  "sSearch": {
    "en": "Search:",
    "fr": "Rechercher&nbsp;:",
    "de": "Suchen",
    "bg": "Търсене:",
    "hr": "Keresés:",
    "cs": "Hledat:",
    "da": "S&oslash;g:",
    "nl": "Zoeken:",
    "et": "Otsi k&otilde;ikide tulemuste seast:",
    "fi": "Etsi:",
    "es": "Buscar:",
    "el": "Αναζήτηση:",
    "hu": "Keresés:",
    "gd": "Cuardaigh:",
    "it": "Cerca:",
    "lv": "Meklēt:",
    "lt": "Ieškoti:",
    "pl": "Szukaj:",
    "pt": "Procurar:",
    "ro": "Caută:",
    "sk": "Hľadať:",
    "sl": "Išči:",
    "sv": "Sök:",
    "nn": "S&oslash;k:",
    "nb": "S&oslash;k:",
    "mt": "Fittex:",
    "ar": "ابحث:",
    "zh": "搜尋:",
    "jp": "検索:",
    "ru": "Поиск:"
  },
  "sZeroRecords": {
    "en": "No matching records found",
    "fr": "Aucun &eacute;l&eacute;ment &agrave; afficher",
    "de": "Keine Einträge vorhanden",
    "bg": "Няма намерени резултати",
    "hr": "Nincs a keresésnek megfelelő találat",
    "cs": "Žádné záznamy nebyly nalezeny",
    "da": "Ingen linjer matcher s&oslash;gningen",
    "nl": "Geen resultaten gevonden",
    "et": "Otsitavat vastet ei leitud.",
    "fi": "Tietoja ei löytynyt",
    "es": "No se encontraron resultados",
    "el": "Δεν βρέθηκαν εγγραφές που να ταιριάζουν",
    "hu": "Nincs a keresésnek megfelelő találat",
    "gd": "Gan aon taifead meaitseáil aimsithe",
    "it": "La ricerca non ha portato alcun risultato.",
    "lv": "Nav atrasti vaicājumam atbilstoši ieraksti",
    "lt": "Įrašų nerasta",
    "pl": "Nie znaleziono pasujących pozycji",
    "pt": "Não foram encontrados resultados",
    "ro": "Nu am găsit nimic - ne pare rău",
    "sk": "Nenašli sa žiadne vyhovujúce záznamy",
    "sl": "Nobeden zapis ne ustreza",
    "sv": "Hittade inga matchande resultat",
    "nn": "Inga linjer treff p&aring; s&oslash;ket",
    "nb": "Ingen linjer matcher s&oslash;ket",
    "mt": "Ma nstabet l-ebda entrata",
    "ar": "لم يعثر على أية سجلات",
    "zh": "沒有符合的結果",
    "jp": "一致するレコードがありません",
    "ru": "Записи отсутствуют."
  },
  "oPaginate_sFirst": {
    "en": "First",
    "fr": "Premier",
    "de": "Erste",
    "bg": "Първа",
    "hr": "Első",
    "cs": "První",
    "da": "F&oslash;rste",
    "nl": "Eerste",
    "et": "Algus",
    "fi": "Ensimmäinen",
    "es": "Primero",
    "el": "Πρώτη",
    "hu": "Első",
    "gd": "An Chéad",
    "it": "Inizio",
    "lv": "Pirmā",
    "lt": "Pirmas",
    "pt": "Primeiro",
    "ro": "Prima",
    "sk": "Prvá",
    "sl": "Prvi",
    "sv": "Första",
    "nn": "Fyrste",
    "nb": "F&oslash;rste",
    "mt": "L-ewwel",
    "ar": "الأول",
    "zh": "第一頁",
    "jp": "先頭",
    "ru": "Первая"
  },
  "oPaginate_sLast": {
    "en": "Last",
    "fr": "Dernier",
    "de": "Letzte",
    "bg": "Последна",
    "hr": "Utolsó",
    "cs": "Poslední",
    "da": "Sidste",
    "nl": "Laatste",
    "et": "Viimane",
    "fi": "Viimeinen",
    "es": "Último",
    "el": "Τελευταία",
    "hu": "Utolsó",
    "gd": "Last",
    "it": "Fine",
    "lv": "Pēdējā",
    "lt": "Paskutinis",
    "pt": "Último",
    "ro": "Ultima",
    "sk": "Posledná",
    "sl": "Zadnji",
    "sv": "Sista",
    "nn": "Siste",
    "nb": "Siste",
    "mt": "L-aħħar",
    "ar": "الأخير",
    "zh": "最後一頁",
    "jp": "最終",
    "ru": "Последняя"
  },
  "oPaginate_sNext": {
    "en": "Next",
    "fr": "Suivant",
    "de": "Nächste",
    "bg": "Следваща",
    "hr": "Következő",
    "cs": "Další",
    "da": "N&aelig;ste",
    "nl": "Volgende",
    "et": "J&auml;rgmine",
    "fi": "Seuraava",
    "es": "Siguiente",
    "el": "Επόμενη",
    "hu": "Következő",
    "gd": "Ar Aghaidh",
    "it": "Successivo",
    "lv": "Nākošā",
    "lt": "Tolimesnis",
    "pt": "Seguinte",
    "ro": "Următoarea",
    "sk": "Nasledujúca",
    "sl": "Nasl.",
    "sv": "Nästa",
    "nn": "Neste",
    "nb": "Neste",
    "mt": "Li jmiss",
    "ar": "التالي",
    "zh": "下一頁",
    "jp": "次",
    "ru": "Следующая"
  },
  "oPaginate_sPrevious": {
    "en": "Previous",
    "fr": "Pr&eacute;c&eacute;dent",
    "de": "Zurück",
    "bg": "Предишна",
    "hr": "Előző",
    "cs": "Předchozí",
    "da": "Forrige",
    "nl": "Vorige",
    "et": "Eelmine",
    "fi": "Edellinen",
    "es": "Anterior",
    "el": "Προηγούμενη",
    "hu": "Előző",
    "gd": "Roimhe Seo",
    "it": "Precedente",
    "lv": "Iepriekšējā",
    "lt": "Ankstesnis",
    "pt": "Anterior",
    "ro": "Precedenta",
    "sk": "Predchádzajúca",
    "sl": "Pred.",
    "sv": "Föregående",
    "nn": "Forrige",
    "nb": "Forrige",
    "mt": "Ta' qabel",
    "ar": "السابق",
    "zh": "上一頁",
    "jp": "前",
    "ru": "Предыдущая"
  },
  "oPaginate_oAria_sSortAscending": {
    "en": ": activate to sort column ascending",
    "fr": ": activer pour trier la colonne par ordre croissant",
    "de": ": aktivieren, um Spalte aufsteigend zu sortieren",
    "hr": ": aktiválja a növekvő rendezéshez",
    "cs": ": aktivujte pro řazení sloupce vzestupně",
    "nl": ": activeer om kolom oplopend te sorteren",
    "fi": ": lajittele sarake nousevasti",
    "es": ": Activar para ordenar la columna de manera ascendente",
    "el": ": ενεργοποιήστε για αύξουσα ταξινόμηση της στήλης",
    "hu": ": aktiválja a növekvő rendezéshez",
    "it": ": attiva per ordinare la colonna in ordine crescente",
    "lv": ": aktivizēt kolonnu, lai kārtotu augoši",
    "pt": ": Ordenar colunas de forma ascendente",
    "sk": ": aktivujte na zoradenie stĺpca vzostupne",
    "sl": ": vključite za naraščujoči sort",
    "sv": ": aktivera för att sortera kolumnen i stigande ordning",
    "nn": ": aktiver for å sortere kolonna stigande",
    "nb": ": aktiver for å sortere kolonnen stigende",
    "zh": ": 升冪排列",
    "jp": ": 列を昇順に並べ替えるにはアクティブにする",
    "ru": ": активировать для сортировки столбца по возрастанию"
  },
  "oPaginate_oAria_sSortDescending": {
    "en": ": activate to sort column descending",
    "fr": ": activer pour trier la colonne par ordre d&eacute;croissant",
    "de": ": aktivieren, um Spalte absteigend zu sortieren",
    "hr": ": aktiválja a csökkenő rendezéshez",
    "cs": ": aktivujte pro řazení sloupce sestupně",
    "nl": ": activeer om kolom aflopend te sorteren",
    "fi": ": lajittele sarake laskevasti",
    "es": ": Activar para ordenar la columna de manera descendente",
    "el": ": ενεργοποιήστε για φθίνουσα ταξινόμηση της στήλης",
    "hu": ": aktiválja a csökkenő rendezéshez",
    "it": ": attiva per ordinare la colonna in ordine decrescente",
    "lv": ": aktivizēt kolonnu, lai kārtotu dilstoši",
    "pt": ": Ordenar colunas de forma descendente",
    "sk": ": aktivujte na zoradenie stĺpca zostupne",
    "sl": ": vključite za padajoči sort",
    "sv": ": aktivera för att sortera kolumnen i fallande ordning",
    "nn": ": aktiver for å sortere kolonna synkande",
    "nb": ": aktiver for å sortere kolonnen synkende",
    "zh": ": 降冪排列",
    "jp": ": 列を降順に並べ替えるにはアクティブにする",
    "ru": ": активировать для сортировки столбца по убыванию"
  },
  "oPaginate_oAria_select_rows_0": {
    "fr": "Aucune ligne séléctionnée",
    "de": "",
    "fi": "Klikkaa riviä valitaksesi sen"
  },
  "oPaginate_oAria_select_rows_1": {
    "fr": "1 ligne séléctionnée",
    "de": "1 Zeile ausgewählt",
    "fi": "Valittuna vain yksi rivi"
  },
  "oPaginate_oAria_select_rows__": {
    "fr": "%d lignes séléctionnées",
    "de": "%d Zeilen ausgewählt",
    "fi": "Valittuna %d riviä"
  },
  "oPaginate_oAria_select_buttons_print": {
    "de": "Drucken"
  },
  "oPaginate_oAria_select_buttons_colvis": {
    "de": "Spalten"
  },
  "oPaginate_oAria_select_buttons_copy": {
    "de": "Kopieren",
    "fi": "Kopioi"
  },
  "oPaginate_oAria_select_buttons_copyTitle": {
    "de": "In Zwischenablage kopieren"
  },
  "oPaginate_oAria_select_buttons_copyKeys": {
    "de": "Taste <i>ctrl</i> oder <i>⌘</i> + <i>C</i> um Tabelle<br>in Zwischenspeicher zu kopieren.<br><br>Um abzubrechen die Nachricht anklicken oder Escape drücken."
  },
  "oPaginate_oAria_select_buttons_copySuccess_1": {
    "de": "1 Spalte kopiert",
    "fi": "Yksi rivi kopioitu leikepöydälle"
  },
  "oPaginate_oAria_select_buttons_copySuccess__": {
    "de": "%d Spalten kopiert",
    "fi": "%d riviä kopioitu leikepöydälle"
  },
  "sUrl": {
    "bg": "",
    "da": "",
    "es": "",
    "el": "",
    "gd": "",
    "lt": "",
    "pt": "",
    "ro": "",
    "nn": "",
    "nb": "",
    "mt": "",
    "ar": ""
  },
  "oPaginate_oAria_select_buttons_copySuccess_copyTitle": {
    "fi": "Kopioi leikepöydälle"
  },
  "oPaginate_oAria_select_buttons_copySuccess_copyKeys": {
    "fi": "Paina <i>ctrl</i> tai <i>⌘</i> + <i>C</i> kopioidaksesi taulukon arvot<br> leikepöydälle. <br><br>Peruuttaaksesi klikkaa tähän tai Esc."
  },
  "sDecimal": {
    "el": ","
  },
  "sSearchPlaceholder": {
    "el": "Αναζήτηση"
  },
  "sThousands": {
    "el": ".",
    "lt": " "
  },
  "sPaginate_sFirst": {
    "pl": "Pierwsza"
  },
  "sPaginate_sPrevious": {
    "pl": "Poprzednia"
  },
  "sPaginate_sNext": {
    "pl": "Następna"
  },
  "sPaginate_sLast": {
    "pl": "Ostatnia"
  },
  "sPaginate_oAria_sSortAscending": {
    "pl": ": aktywuj, by posortować kolumnę rosnąco"
  },
  "sPaginate_oAria_sSortDescending": {
    "pl": ": aktywuj, by posortować kolumnę malejąco"
  }
}